{
    "onload.py": {
        "ID": "59d2b294-9626-41a4-abbe-37c348806c33", 
        "Left": "0", 
        "Name": "onload", 
        "State": "true", 
        "Top": "0"
    }, 
    "role_dialog_fill.py": {
        "ID": "4f2de0d7-ca3b-493f-b61a-1b0775e0cca5", 
        "Left": "844", 
        "Name": "role_dialog_fill", 
        "State": "true", 
        "Top": "554"
    }, 
    "role_update.py": {
        "ID": "7f0217e5-3563-4081-bcad-6d3320f35160", 
        "Left": "597", 
        "Name": "role_update", 
        "State": "true", 
        "Top": "96"
    }
}