{
    "actions": [
        {
            "ID": "0C364E6D-8CD1-3812-9EE8-6C6CFE3F1007", 
            "Left": "639", 
            "MethodName": "resizeTo", 
            "ObjTgtID": "8bfe8ac5-182c-4215-9abc-276eea8fab7c", 
            "Params": [
                [
                    "width", 
                    "\"267\""
                ], 
                [
                    "height", 
                    "(jQuery(\"#o_0a7b487f_7955_40e9_83ec_3e94ffa62ddd .dynatree-container\").height()<jQuery(window).height() && jQuery(\"#o_13fcd121_8974_4b9e_9cb3_d8f6680eedd9 .table\").height()<jQuery(window).height())?jQuery(window).height()-90:((jQuery(\"#o_13fcd121_8974_4b9e_9cb3_d8f6680eedd9 .table\").height()<jQuery(\"#o_0a7b487f_7955_40e9_83ec_3e94ffa62ddd .dynatree-container\").height())?jQuery(\"#o_0a7b487f_7955_40e9_83ec_3e94ffa62ddd .dynatree-container\").height()+20:jQuery(\"#o_13fcd121_8974_4b9e_9cb3_d8f6680eedd9 .table\").height()+20)"
                ]
            ], 
            "State": "true", 
            "Top": "702"
        }, 
        {
            "ID": "361B887D-92FB-499F-AFF8-5C817B0F8C84", 
            "Left": "919", 
            "MethodName": "show", 
            "ObjTgtID": "e9aed224-fa46-4562-96b2-0404e81b1adb", 
            "Params": [
                [
                    "fade", 
                    "300"
                ]
            ], 
            "State": "true", 
            "Top": "416"
        }, 
        {
            "ID": "3996A4A5-4DB8-6BD2-16EE-6C6CBEE609B2", 
            "Left": "448", 
            "MethodName": "resizeTo", 
            "ObjTgtID": "d3bdfb7e-24ca-4bfc-a044-9aa0a8922c04", 
            "Params": [
                [
                    "width", 
                    "\"352\""
                ], 
                [
                    "height", 
                    "(jQuery(\"#o_0a7b487f_7955_40e9_83ec_3e94ffa62ddd .dynatree-container\").height()<jQuery(window).height() && jQuery(\"#o_13fcd121_8974_4b9e_9cb3_d8f6680eedd9 .table\").height()<jQuery(window).height())?jQuery(window).height()-90:((jQuery(\"#o_13fcd121_8974_4b9e_9cb3_d8f6680eedd9 .table\").height()<jQuery(\"#o_0a7b487f_7955_40e9_83ec_3e94ffa62ddd .dynatree-container\").height())?jQuery(\"#o_0a7b487f_7955_40e9_83ec_3e94ffa62ddd .dynatree-container\").height()+20:jQuery(\"#o_13fcd121_8974_4b9e_9cb3_d8f6680eedd9 .table\").height()+20)"
                ]
            ], 
            "State": "true", 
            "Top": "627"
        }, 
        {
            "ID": "89DDAB3F-016D-4E0C-9829-BB4F69FB071A", 
            "Left": "604", 
            "MethodName": "hide", 
            "ObjTgtID": "e9aed224-fa46-4562-96b2-0404e81b1adb", 
            "Params": [
                [
                    "fade", 
                    "300"
                ]
            ], 
            "State": "true", 
            "Top": "105"
        }, 
        {
            "ID": "98877573-4E51-4628-93AC-AF4D086CCE16", 
            "Left": "1308", 
            "MethodName": "moveTo", 
            "ObjTgtID": "75b065ef-dec8-4ae4-b761-5e972450fe61", 
            "Params": [
                [
                    "newX", 
                    "710"
                ], 
                [
                    "newY", 
                    "69"
                ], 
                [
                    "Effect", 
                    "300"
                ]
            ], 
            "State": "true", 
            "Top": "29"
        }, 
        {
            "ID": "AA147963-92AF-4E9B-99B5-19D28EA72A6D", 
            "Left": "941", 
            "MethodName": "show", 
            "ObjTgtID": "3020da81-ad59-41d7-a181-04166b472707", 
            "Params": [
                [
                    "fade", 
                    "300"
                ]
            ], 
            "State": "true", 
            "Top": "70"
        }, 
        {
            "ID": "C355E6A4-B54F-7609-BA66-6C6CEB286B87", 
            "Left": "660", 
            "MethodName": "resizeTo", 
            "ObjTgtID": "e2cfe8af-ad7e-4055-907e-437f095bb2fc", 
            "Params": [
                [
                    "width", 
                    "\"337\""
                ], 
                [
                    "height", 
                    "(jQuery(\"#o_0a7b487f_7955_40e9_83ec_3e94ffa62ddd .dynatree-container\").height()<jQuery(window).height() && jQuery(\"#o_13fcd121_8974_4b9e_9cb3_d8f6680eedd9 .table\").height()<jQuery(window).height())?jQuery(window).height()-90:((jQuery(\"#o_13fcd121_8974_4b9e_9cb3_d8f6680eedd9 .table\").height()<jQuery(\"#o_0a7b487f_7955_40e9_83ec_3e94ffa62ddd .dynatree-container\").height())?jQuery(\"#o_0a7b487f_7955_40e9_83ec_3e94ffa62ddd .dynatree-container\").height()+20:jQuery(\"#o_13fcd121_8974_4b9e_9cb3_d8f6680eedd9 .table\").height()+20)"
                ]
            ], 
            "State": "true", 
            "Top": "844"
        }, 
        {
            "ID": "C742500C-4158-44C1-AFC0-21641BCBC307", 
            "Left": "338", 
            "MethodName": "moveTo", 
            "ObjTgtID": "75b065ef-dec8-4ae4-b761-5e972450fe61", 
            "Params": [
                [
                    "newX", 
                    "710"
                ], 
                [
                    "newY", 
                    "89"
                ], 
                [
                    "Effect", 
                    "300"
                ]
            ], 
            "State": "true", 
            "Top": "52"
        }, 
        {
            "ID": "EBB24116-5310-9460-4C26-6C77C2622833", 
            "Left": "464", 
            "MethodName": "resizeTo", 
            "ObjTgtID": "a7e4daa8-ea76-4591-8e39-eadef0fed90b", 
            "Params": [
                [
                    "width", 
                    "\"965\""
                ], 
                [
                    "height", 
                    "(jQuery(\"#o_0a7b487f_7955_40e9_83ec_3e94ffa62ddd .dynatree-container\").height()<jQuery(window).height() && jQuery(\"#o_13fcd121_8974_4b9e_9cb3_d8f6680eedd9 .table\").height()<jQuery(window).height())?jQuery(window).height()-90:((jQuery(\"#o_13fcd121_8974_4b9e_9cb3_d8f6680eedd9 .table\").height()<jQuery(\"#o_0a7b487f_7955_40e9_83ec_3e94ffa62ddd .dynatree-container\").height())?jQuery(\"#o_0a7b487f_7955_40e9_83ec_3e94ffa62ddd .dynatree-container\").height()+20:jQuery(\"#o_13fcd121_8974_4b9e_9cb3_d8f6680eedd9 .table\").height()+20)"
                ]
            ], 
            "State": "true", 
            "Top": "806"
        }, 
        {
            "ID": "F6408D1B-9AD6-493D-969C-D297538E0436", 
            "Left": "89", 
            "MethodName": "hide", 
            "ObjTgtID": "3020da81-ad59-41d7-a181-04166b472707", 
            "Params": [
                [
                    "fade", 
                    "300"
                ]
            ], 
            "State": "true", 
            "Top": "107"
        }
    ], 
    "events": [
        {
            "actions": [
                "C742500C-4158-44C1-AFC0-21641BCBC307", 
                "24c9aad6-2abf-4180-ad19-4318edf55a39", 
                "89DDAB3F-016D-4E0C-9829-BB4F69FB071A", 
                "F6408D1B-9AD6-493D-969C-D297538E0436"
            ], 
            "ContainerID": "c6021746-cbf1-4f56-bc90-4c1df4dfbaef", 
            "Left": "468", 
            "Name": "click", 
            "ObjSrcID": "3020da81-ad59-41d7-a181-04166b472707", 
            "State": "false", 
            "Top": "460"
        }, 
        {
            "actions": [
                "3996A4A5-4DB8-6BD2-16EE-6C6CBEE609B2", 
                "0C364E6D-8CD1-3812-9EE8-6C6CFE3F1007", 
                "C355E6A4-B54F-7609-BA66-6C6CEB286B87", 
                "EBB24116-5310-9460-4C26-6C77C2622833"
            ], 
            "ContainerID": "c6021746-cbf1-4f56-bc90-4c1df4dfbaef", 
            "Left": "4", 
            "Name": "load", 
            "ObjSrcID": "c6021746-cbf1-4f56-bc90-4c1df4dfbaef", 
            "State": "false", 
            "Top": "818"
        }, 
        {
            "actions": [
                "3996A4A5-4DB8-6BD2-16EE-6C6CBEE609B2", 
                "0C364E6D-8CD1-3812-9EE8-6C6CFE3F1007", 
                "C355E6A4-B54F-7609-BA66-6C6CEB286B87", 
                "EBB24116-5310-9460-4C26-6C77C2622833"
            ], 
            "ContainerID": "c6021746-cbf1-4f56-bc90-4c1df4dfbaef", 
            "Left": "1", 
            "Name": "resize", 
            "ObjSrcID": "c6021746-cbf1-4f56-bc90-4c1df4dfbaef", 
            "State": "false", 
            "Top": "732"
        }, 
        {
            "actions": [
                "6676bf9d-4786-4e84-9496-b413b51a1c4e", 
                "C742500C-4158-44C1-AFC0-21641BCBC307", 
                "89DDAB3F-016D-4E0C-9829-BB4F69FB071A", 
                "F6408D1B-9AD6-493D-969C-D297538E0436"
            ], 
            "ContainerID": "c6021746-cbf1-4f56-bc90-4c1df4dfbaef", 
            "Left": "12", 
            "Name": "activate", 
            "ObjSrcID": "0a7b487f-7955-40e9-83ec-3e94ffa62ddd", 
            "State": "false", 
            "Top": "460"
        }, 
        {
            "actions": [
                "3996A4A5-4DB8-6BD2-16EE-6C6CBEE609B2", 
                "0C364E6D-8CD1-3812-9EE8-6C6CFE3F1007", 
                "EBB24116-5310-9460-4C26-6C77C2622833", 
                "C355E6A4-B54F-7609-BA66-6C6CEB286B87"
            ], 
            "ContainerID": "c6021746-cbf1-4f56-bc90-4c1df4dfbaef", 
            "Left": "1", 
            "Name": "expand", 
            "ObjSrcID": "0a7b487f-7955-40e9-83ec-3e94ffa62ddd", 
            "State": "true", 
            "Top": "852"
        }, 
        {
            "actions": [
                "361B887D-92FB-499F-AFF8-5C817B0F8C84", 
                "AA147963-92AF-4E9B-99B5-19D28EA72A6D", 
                "98877573-4E51-4628-93AC-AF4D086CCE16", 
                "9dfe11fc-a71c-42fa-889e-e2bda147d7ac"
            ], 
            "ContainerID": "c6021746-cbf1-4f56-bc90-4c1df4dfbaef", 
            "Left": "1148", 
            "Name": "rowsselected", 
            "ObjSrcID": "2b25e375-2c51-41ff-8b32-40f1f9a1cfe9", 
            "State": "true", 
            "Top": "279"
        }, 
        {
            "actions": [
                "C742500C-4158-44C1-AFC0-21641BCBC307", 
                "a57462cd-74d4-43d7-8305-544c28a15e01", 
                "89DDAB3F-016D-4E0C-9829-BB4F69FB071A", 
                "F6408D1B-9AD6-493D-969C-D297538E0436"
            ], 
            "ContainerID": "c6021746-cbf1-4f56-bc90-4c1df4dfbaef", 
            "Left": "689", 
            "Name": "click", 
            "ObjSrcID": "e9aed224-fa46-4562-96b2-0404e81b1adb", 
            "State": "false", 
            "Top": "463"
        }, 
        {
            "actions": [
                "C742500C-4158-44C1-AFC0-21641BCBC307", 
                "bff13c39-8f4d-4dd4-9cfc-1ca63a9c0822", 
                "89DDAB3F-016D-4E0C-9829-BB4F69FB071A", 
                "F6408D1B-9AD6-493D-969C-D297538E0436"
            ], 
            "ContainerID": "c6021746-cbf1-4f56-bc90-4c1df4dfbaef", 
            "Left": "239", 
            "Name": "rowsselected", 
            "ObjSrcID": "13fcd121-8974-4b9e-9cb3-d8f6680eedd9", 
            "State": "false", 
            "Top": "458"
        }, 
        {
            "actions": [
                "3996A4A5-4DB8-6BD2-16EE-6C6CBEE609B2", 
                "0C364E6D-8CD1-3812-9EE8-6C6CFE3F1007", 
                "EBB24116-5310-9460-4C26-6C77C2622833", 
                "C355E6A4-B54F-7609-BA66-6C6CEB286B87"
            ], 
            "ContainerID": "c6021746-cbf1-4f56-bc90-4c1df4dfbaef", 
            "Left": "929", 
            "Name": "load", 
            "ObjSrcID": "13fcd121-8974-4b9e-9cb3-d8f6680eedd9", 
            "State": "true", 
            "Top": "694"
        }
    ]
}